.gitignore
CHANGELOG.md
LICENSE
Makefile
README.md
changelog.yaml
changelog_entry.yaml
setup.py
.github/changelog_template.md
.github/get-changelog-diff.sh
.github/has-functional-changes.sh
.github/is-version-number-acceptable.sh
.github/publish-git-tag.sh
.github/workflows/pr.yml
.github/workflows/push.yml
.vscode/launch.json
dashboard/app.py
dashboard/experiments/gpt4_api_user.py
dashboard/experiments/requirements.txt
gcp/Dockerfile
gcp/README.md
gcp/bump_country_package.py
gcp/dispatch.yaml
gcp/export.py
gcp/policyengine_api/Dockerfile
gcp/policyengine_api/app.yaml
gcp/policyengine_api/start.sh
policyengine_api/api.py
policyengine_api/constants.py
policyengine_api/country.py
policyengine_api/worker.py
policyengine_api.egg-info/PKG-INFO
policyengine_api.egg-info/SOURCES.txt
policyengine_api.egg-info/dependency_links.txt
policyengine_api.egg-info/entry_points.txt
policyengine_api.egg-info/requires.txt
policyengine_api.egg-info/top_level.txt
policyengine_api/data/README.md
policyengine_api/data/__init__.py
policyengine_api/data/data.py
policyengine_api/data/initialise.sql
policyengine_api/data/initialise_local.sql
policyengine_api/endpoints/__init__.py
policyengine_api/endpoints/analysis.py
policyengine_api/endpoints/home.py
policyengine_api/endpoints/household.py
policyengine_api/endpoints/metadata.py
policyengine_api/endpoints/policy.py
policyengine_api/endpoints/economy/__init__.py
policyengine_api/endpoints/economy/compare.py
policyengine_api/endpoints/economy/economy.py
policyengine_api/endpoints/economy/reform_impact.py
policyengine_api/endpoints/economy/single_economy.py
policyengine_api/endpoints/search/README.md
policyengine_api/endpoints/search/__init__.py
policyengine_api/endpoints/search/create_embeddings.py
policyengine_api/endpoints/search/search.py
policyengine_api/utils/__init__.py
policyengine_api/utils/json.py
tests/api/test_api.py
tests/api/test_hello_world.yaml
tests/api/test_liveness.yaml
tests/api/test_readiness.yaml
tests/api/test_uk_baseline_policy.yaml
tests/api/test_uk_metadata.yaml