Metadata-Version: 2.1
Name: policyengine-api
Version: 1.1.2
Summary: PolicyEngine API
Author: PolicyEngine
Author-email: hello@policyengine.org
License: UNKNOWN
Platform: UNKNOWN
License-File: LICENSE
